.VERSION
AUTHORS.rst
CONTRIBUTING.rst
HISTORY.rst
LICENSE
MANIFEST.in
Pipfile
Pipfile.lock
README.rst
USAGE.rst
dev-requirements.txt
requirements.txt
setup.cfg
setup.py
docs/Makefile
docs/authors.rst
docs/conf.py
docs/contributing.rst
docs/history.rst
docs/index.rst
docs/installation.rst
docs/modules.rst
docs/readme.rst
docs/usage.rst
docs/wikiseriessjoerdlib.rst
tests/test_wikiseriessjoerdlib.py
wikiseriessjoerdlib/.VERSION
wikiseriessjoerdlib/AUTHORS.rst
wikiseriessjoerdlib/CONTRIBUTING.rst
wikiseriessjoerdlib/HISTORY.rst
wikiseriessjoerdlib/LICENSE
wikiseriessjoerdlib/Pipfile
wikiseriessjoerdlib/Pipfile.lock
wikiseriessjoerdlib/README.rst
wikiseriessjoerdlib/USAGE.rst
wikiseriessjoerdlib/__init__.py
wikiseriessjoerdlib/_version.py
wikiseriessjoerdlib/dev-requirements.txt
wikiseriessjoerdlib/requirements.txt
wikiseriessjoerdlib/wikiseriessjoerdlib.py
wikiseriessjoerdlib/wikiseriessjoerdlibexceptions.py
wikiseriessjoerdlib.egg-info/PKG-INFO
wikiseriessjoerdlib.egg-info/SOURCES.txt
wikiseriessjoerdlib.egg-info/dependency_links.txt
wikiseriessjoerdlib.egg-info/not-zip-safe
wikiseriessjoerdlib.egg-info/requires.txt
wikiseriessjoerdlib.egg-info/top_level.txt