Metadata-Version: 2.1
Name: wikiseriessjoerdlib
Version: 0.1.2
Summary: A libary interfacing with Wikipedia to retrieve tv series information.
Home-page: https://github.com/sjoerdvdbos/wikiseriessjoerdlib
Author: Sjoerd van den Bos
Author-email: test@example.com
License: MIT
Keywords: wikiseriessjoerdlib wiki series tv series
Classifier: Development Status :: 3 - Alpha
Classifier: Intended Audience :: Developers
Classifier: License :: OSI Approved :: MIT License
Classifier: Natural Language :: English
Classifier: Programming Language :: Python :: 3.9
License-File: LICENSE
License-File: AUTHORS.rst
